real_estate_realtor_com_imp_local/__init__.py
real_estate_realtor_com_imp_local/realtor.py
real_estate_realtor_com_imp_local-0.0.28.dist-info/METADATA
real_estate_realtor_com_imp_local-0.0.28.dist-info/WHEEL
real_estate_realtor_com_imp_local-0.0.28.dist-info/top_level.txt
real_estate_realtor_com_imp_local-0.0.28.dist-info/RECORD
