Metadata-Version: 2.4
Name: real-estate-realtor-com-imp-local
Version: 0.0.28
Summary: PyPI Package for Real estate python package
Home-page: https://github.com/circles-zone/real-estate-realtor-com-imp-local-python-package
Author: Circles
Author-email: info@circles.ai
Classifier: Programming Language :: Python :: 3
Classifier: License :: Other/Proprietary License
Classifier: Operating System :: OS Independent
Requires-Dist: importer-local>=0.0.33
Requires-Dist: logger-local>=0.0.55
Requires-Dist: database-mysql-local>=0.0.290
Requires-Dist: location-local>=0.0.23
Requires-Dist: entity-type-local>=0.0.12
Requires-Dist: selenium
Dynamic: author
Dynamic: author-email
Dynamic: classifier
Dynamic: description
Dynamic: description-content-type
Dynamic: home-page
Dynamic: requires-dist
Dynamic: summary
